awscost/__init__.py
awscost/billing.py
awscost/commands.py
awscost/constants.py
awscost/cost_explorer.py
awscost/cost_explorer_client.py
awscost/date_util.py
awscost/logger.py
awscost/util.py
awscost/validator.py
awscost-0.0.6.data/scripts/awscost
awscost-0.0.6.dist-info/METADATA
awscost-0.0.6.dist-info/WHEEL
awscost-0.0.6.dist-info/entry_points.txt
awscost-0.0.6.dist-info/top_level.txt
awscost-0.0.6.dist-info/RECORD
