Metadata-Version: 2.1
Name: awscost
Version: 0.0.6
Summary: Command Line utility for cost of aws.
Home-page: https://github.com/toyama0919/awscost
Author: Hiroshi Toyama
Author-email: toyama0919@gmail.com
License: MIT
Keywords: awscost tool
Platform: UNKNOWN
Classifier: Programming Language :: Python :: 3.6
Classifier: Programming Language :: Python :: 3.7
Requires-Dist: tabulate
Requires-Dist: boto3
Requires-Dist: click (>=7.0)
